sgaimdbpull/__init__.py
sgaimdbpull/imdb.py
sgaimdbpull-1.0.1.dist-info/METADATA
sgaimdbpull-1.0.1.dist-info/WHEEL
sgaimdbpull-1.0.1.dist-info/top_level.txt
sgaimdbpull-1.0.1.dist-info/RECORD
